MANIFEST.in
README.md
setup.py
bin/epic2
bin/epic2-bw
bin/epic2-df
epic2/__init__.py
epic2/bigwig.py
epic2/main.py
epic2/version.py
epic2.egg-info/PKG-INFO
epic2.egg-info/SOURCES.txt
epic2.egg-info/dependency_links.txt
epic2.egg-info/requires.txt
epic2.egg-info/top_level.txt
epic2/chromsizes/ailMel1.chromsizes
epic2/chromsizes/anoCar2.chromsizes
epic2/chromsizes/apiMel1.chromsizes
epic2/chromsizes/aplCal1.chromsizes
epic2/chromsizes/aquChr2.chromsizes
epic2/chromsizes/balAcu1.chromsizes
epic2/chromsizes/braFlo1.chromsizes
epic2/chromsizes/calJac1.chromsizes
epic2/chromsizes/calJac3.chromsizes
epic2/chromsizes/cavPor3.chromsizes
epic2/chromsizes/ce10.chromsizes
epic2/chromsizes/ce11.chromsizes
epic2/chromsizes/cerSim1.chromsizes
epic2/chromsizes/chlSab2.chromsizes
epic2/chromsizes/chrPic1.chromsizes
epic2/chromsizes/danRer10.chromsizes
epic2/chromsizes/danRer3.chromsizes
epic2/chromsizes/danRer4.chromsizes
epic2/chromsizes/danRer5.chromsizes
epic2/chromsizes/danRer6.chromsizes
epic2/chromsizes/danRer7.chromsizes
epic2/chromsizes/dm3.chromsizes
epic2/chromsizes/dm6.chromsizes
epic2/chromsizes/echTel2.chromsizes
epic2/chromsizes/equCab1.chromsizes
epic2/chromsizes/equCab2.chromsizes
epic2/chromsizes/eriEur1.chromsizes
epic2/chromsizes/eriEur2.chromsizes
epic2/chromsizes/fr1.chromsizes
epic2/chromsizes/fr2.chromsizes
epic2/chromsizes/galVar1.chromsizes
epic2/chromsizes/gasAcu1.chromsizes
epic2/chromsizes/geoFor1.chromsizes
epic2/chromsizes/gorGor3.chromsizes
epic2/chromsizes/gorGor4.chromsizes
epic2/chromsizes/gorGor5.chromsizes
epic2/chromsizes/hetGla1.chromsizes
epic2/chromsizes/hetGla2.chromsizes
epic2/chromsizes/hg18.chromsizes
epic2/chromsizes/hg19.chromsizes
epic2/chromsizes/hg38.chromsizes
epic2/chromsizes/loxAfr3.chromsizes
epic2/chromsizes/macEug2.chromsizes
epic2/chromsizes/melGal1.chromsizes
epic2/chromsizes/melGal5.chromsizes
epic2/chromsizes/micMur2.chromsizes
epic2/chromsizes/mm10.chromsizes
epic2/chromsizes/mm9.chromsizes
epic2/chromsizes/monDom4.chromsizes
epic2/chromsizes/monDom5.chromsizes
epic2/chromsizes/myoLuc2.chromsizes
epic2/chromsizes/nanPar1.chromsizes
