Metadata-Version: 1.1
Name: epic2
Version: 0.0.52
Summary: Ultraperformant ChIP-Seq broad peak/domain finder.
Home-page: http://github.com/endrebak/epic2
Author: Endre Bakken Stovner
Author-email: endrebak85@gmail.com
License: MIT
Keywords: ChIP-Seq
Platform: UNKNOWN
Classifier: Programming Language :: Python :: 2.7
Classifier: Programming Language :: Python :: 3
Classifier: Development Status :: 4 - Beta
Classifier: Environment :: Other Environment
Classifier: Intended Audience :: Developers
Classifier: Intended Audience :: Science/Research
Classifier: License :: OSI Approved :: MIT License
Classifier: Operating System :: POSIX :: Linux
Classifier: Operating System :: MacOS :: MacOS X
Classifier: Topic :: Scientific/Engineering
